django_dataclasses/__init__.py
django_dataclasses/api.py
django_dataclasses/auth.py
django_dataclasses/dataclasses.py
django_dataclasses/iterable.py
django_dataclasses/schema.py
django_dataclasses/version.py
django_dataclasses/management/__init__.py
django_dataclasses/management/commands/__init__.py
django_dataclasses/management/commands/openapi_export.py
django_dataclasses/management/commands/tests/__init__.py
django_dataclasses/management/commands/tests/test_openapi_export.py
django_dataclasses/tests/__init__.py
django_dataclasses/tests/test_api.py
django_dataclasses/tests/test_auth.py
django_dataclasses/tests/test_schema.py
django_dataclasses-0.2.2.dist-info/LICENSE
django_dataclasses-0.2.2.dist-info/METADATA
django_dataclasses-0.2.2.dist-info/WHEEL
django_dataclasses-0.2.2.dist-info/pbr.json
django_dataclasses-0.2.2.dist-info/top_level.txt
django_dataclasses-0.2.2.dist-info/RECORD
