Metadata-Version: 2.1
Name: django-dataclasses
Version: 0.2.2
Summary: Implement a JSON API using dataclasses
Home-page: https://gitlab.com/roivant/oss/django-dataclasses
Author: Roivant Sciences
Author-email: vant.tech.eng@roivant.com
License: UNKNOWN
Platform: UNKNOWN
Classifier: Topic :: Internet :: WWW/HTTP :: Dynamic Content
Classifier: Intended Audience :: Developers
Classifier: Programming Language :: Python
Classifier: Programming Language :: Python :: 3
Classifier: Development Status :: 4 - Beta
Classifier: Operating System :: OS Independent
Classifier: License :: OSI Approved :: Apache Software License
Requires-Python: >=3.7
License-File: LICENSE
Requires-Dist: apispec
Requires-Dist: django
Requires-Dist: dataclasses-jsonschema
